wesci/__init__.py
wesci/config.py
wesci/figures.py
wesci/files.py
wesci/hash.py
wesci/imports.py
wesci/logger.py
wesci/params.py
wesci/timer.py
wesci-0.6.2.dist-info/DESCRIPTION.rst
wesci-0.6.2.dist-info/METADATA
wesci-0.6.2.dist-info/RECORD
wesci-0.6.2.dist-info/WHEEL
wesci-0.6.2.dist-info/metadata.json
wesci-0.6.2.dist-info/top_level.txt
