Metadata-Version: 2.0
Name: wesci
Version: 0.6.2
Summary: We-Sci's seamless python toolset for tracking and managing research data
Home-page: https://github.com/We-Sci/public_wesci_python_logger
Author: We-Sci
Author-email: info@we-sci.com
License: MIT
Keywords: biology computational provenance we-sci toolset
Platform: UNKNOWN
Classifier: Development Status :: 3 - Alpha
Classifier: Intended Audience :: Science/Research
Classifier: Topic :: Scientific/Engineering :: Bio-Informatics
Classifier: License :: OSI Approved :: MIT License
Classifier: Programming Language :: Python :: 2.7
Classifier: Programming Language :: Python :: 3
Requires-Python: >=2.7.9
Requires-Dist: Pillow (>=4.2)
Requires-Dist: matplotlib (>=2.0)
Requires-Dist: pandas (>=0.14)
Requires-Dist: requests (>=2.18)
